{
    "fluentMethods": true,
    "relationships": [
        {
            "relationshipName": "nomination",
            "otherEntityName": "nomination",
            "relationshipType": "one-to-many",
            "otherEntityRelationshipName": "person"
        }
    ],
    "fields": [
        {
            "fieldName": "firstName",
            "fieldType": "String",
            "fieldValidateRules": [
                "required"
            ]
        },
        {
            "fieldName": "lastName",
            "fieldType": "String",
            "fieldValidateRules": [
                "required"
            ]
        },
        {
            "fieldName": "growCount",
            "fieldType": "Integer",
            "fieldValidateRules": [
                "required",
                "min"
            ],
            "fieldValidateRulesMin": 0
        },
        {
            "fieldName": "createCount",
            "fieldType": "Integer",
            "fieldValidateRules": [
                "required",
                "min"
            ],
            "fieldValidateRulesMin": 0
        },
        {
            "fieldName": "togetherCount",
            "fieldType": "Integer",
            "fieldValidateRules": [
                "required",
                "min"
            ],
            "fieldValidateRulesMin": 0
        },
        {
            "fieldName": "expressCount",
            "fieldType": "Integer",
            "fieldValidateRules": [
                "required",
                "min"
            ],
            "fieldValidateRulesMin": 0
        }
    ],
    "changelogDate": "20161027220755",
    "dto": "no",
    "service": "serviceImpl",
    "entityTableName": "person",
    "pagination": "infinite-scroll"
}
